<?xml version="1.0" encoding="UTF-8"?>
<akn:akomaNtoso xmlns:akn="http://docs.oasis-open.org/legaldocml/ns/akn/3.0"><akn:act><akn:meta><akn:identification source="#cosilico"><akn:FRBRWork prescriptive="true" authoritative="true"><akn:FRBRuri value="/akn/us/usc/42/1397" /><akn:FRBRdate date="2025-12-31" name="retrieval" /><akn:FRBRauthor href="#us-congress" /><akn:FRBRcountry value="us" /></akn:FRBRWork><akn:FRBRExpression><akn:FRBRuri value="/akn/us/usc/42/1397/eng@2025" /><akn:FRBRdate date="2025-12-31" /><akn:FRBRauthor href="#cosilico" /><akn:FRBRlanguage language="en" /></akn:FRBRExpression><akn:FRBRManifestation><akn:FRBRuri value="/akn/us/usc/42/1397/eng@2025/main.xml" /><akn:FRBRdate date="2025-12-31" /><akn:FRBRauthor href="#cosilico" /></akn:FRBRManifestation></akn:identification></akn:meta><akn:body><akn:section eId="sec_1397"><akn:num>1397</akn:num><akn:heading>Purposes of division; authorization of appropriations</akn:heading><akn:content><akn:p>§ 1397. Purposes of division; authorization of appropriations
For the purposes of consolidating Federal assistance to States for social services into a single grant, increasing State flexibility in using social service grants, and encouraging each State, as far as practicable under the conditions in that State, to furnish services directed at the goals of—(1) achieving or maintaining economic self-support to prevent, reduce, or eliminate dependency;

(2) achieving or maintaining self-sufficiency, including reduction or prevention of dependency;

(3) preventing or remedying neglect, abuse, or exploitation of children and adults unable to protect their own interests, or preserving, rehabilitating or reuniting families;

(4) preventing or reducing inappropriate institutional care by providing for community-based care, home-based care, or other forms of less intensive care; and

(5) securing referral or admission for institutional care when other forms of care are not appropriate, or providing services to individuals in institutions,


there are authorized to be appropriated for each fiscal year such sums as may be necessary to carry out the purposes of this division.
(Aug. 14, 1935, ch. 531, title XX, § 2001, as added Pub. L. 97–35, title XXIII, § 2352(a), Aug. 13, 1981, 95 Stat. 867; amended Pub. L. 111–148, title VI, § 6703(d)(1), Mar. 23, 2010, 124 Stat. 803.)

Editorial Notes
Prior ProvisionsA prior section 1397, act Aug. 14, 1935, ch. 531, title XX, § 2001, as added Jan. 4, 1975, Pub. L. 93–647, § 2, 88 Stat. 2337; amended June 17, 1980, Pub. L. 96–272, title II, § 207(b), 94 Stat. 526, authorized appropriations to carry out former provisions of this subchapter, prior to the general revision of this subchapter by section 2352(a) of Pub. L. 97–35.

Amendments2010—Pub. L. 111–148, § 6703(d)(1)(B), which directed substitution of “this division” for “this subchapter” wherever appearing in subtitle 1 of title XX of act Aug. 14, 1935, was executed to the concluding prov</akn:p></akn:content><akn:subsection eId="subsec_1397_1"><akn:num>(1)</akn:num><akn:content><akn:p>(1) achieving or maintaining economic self-support to prevent, reduce, or eliminate dependency;</akn:p></akn:content></akn:subsection><akn:subsection eId="subsec_1397_2"><akn:num>(2)</akn:num><akn:content><akn:p>(2) achieving or maintaining self-sufficiency, including reduction or prevention of dependency;</akn:p></akn:content></akn:subsection><akn:subsection eId="subsec_1397_3"><akn:num>(3)</akn:num><akn:content><akn:p>(3) preventing or remedying neglect, abuse, or exploitation of children and adults unable to protect their own interests, or preserving, rehabilitating or reuniting families;</akn:p></akn:content></akn:subsection><akn:subsection eId="subsec_1397_4"><akn:num>(4)</akn:num><akn:content><akn:p>(4) preventing or reducing inappropriate institutional care by providing for community-based care, home-based care, or other forms of less intensive care; and</akn:p></akn:content></akn:subsection><akn:subsection eId="subsec_1397_5"><akn:num>(5)</akn:num><akn:content><akn:p>(5) securing referral or admission for institutional care when other forms of care are not appropriate, or providing services to individuals in institutions,</akn:p></akn:content></akn:subsection></akn:section></akn:body></akn:act></akn:akomaNtoso>