<?xml version="1.0" encoding="UTF-8"?>
<akn:akomaNtoso xmlns:akn="http://docs.oasis-open.org/legaldocml/ns/akn/3.0"><akn:act><akn:meta><akn:identification source="#cosilico"><akn:FRBRWork prescriptive="true" authoritative="true"><akn:FRBRuri value="/akn/us/usc/42/4052" /><akn:FRBRdate date="2025-12-31" name="retrieval" /><akn:FRBRauthor href="#us-congress" /><akn:FRBRcountry value="us" /></akn:FRBRWork><akn:FRBRExpression><akn:FRBRuri value="/akn/us/usc/42/4052/eng@2025" /><akn:FRBRdate date="2025-12-31" /><akn:FRBRauthor href="#cosilico" /><akn:FRBRlanguage language="en" /></akn:FRBRExpression><akn:FRBRManifestation><akn:FRBRuri value="/akn/us/usc/42/4052/eng@2025/main.xml" /><akn:FRBRdate date="2025-12-31" /><akn:FRBRauthor href="#cosilico" /></akn:FRBRManifestation></akn:identification></akn:meta><akn:body><akn:section eId="sec_4052"><akn:num>4052</akn:num><akn:heading>Agreements with flood insurance pool</akn:heading><akn:content><akn:p>§ 4052. Agreements with flood insurance pool(a) AuthorizationThe Administrator is authorized to enter into such agreements with the pool formed or otherwise created under this part as he deems necessary to carry out the purposes of this chapter.


(b) Terms and conditionsSuch agreements shall specify—(1) the terms and conditions under which risk capital will be available for the adjustment and payment of claims,

(2) the terms and conditions under which the pool (and the companies and other insurers participating therein) shall participate in premiums received and profits or losses realized or sustained,

(3) the maximum amount of profit, established by the Administrator and set forth in the schedules prescribed under section 4018 of this title, which may be realized by such pool (and the companies and other insurers participating therein),

(4) the terms and conditions under which operating costs and allowances set forth in the schedules prescribed under section 4018 of this title may be paid, and

(5) the terms and conditions under which premium equalization payments under section 4054 of this title will be made and reinsurance claims under section 4055 of this title will be paid.


(c) Additional provisionsIn addition, such agreements shall contain such provisions as the Administrator finds necessary to assure that—(1) no insurance company or other insurer which meets the requirements prescribed under section 4051(b) of this title, and which has indicated an intention to participate in the flood insurance program on a risk-sharing basis, will be excluded from participating in the pool,

(2) the insurance companies and other insurers participating in the pool will take whatever action may be necessary to provide continuity of flood insurance coverage or reinsurance by the pool, and

(3) any insurance companies and other insurers, insurance agents and brokers, and insurance adjustment organizations will be permitted to cooperate with the pool as fiscal agents or ot</akn:p></akn:content><akn:subsection eId="subsec_4052_a"><akn:num>(a)</akn:num><akn:heading>Authorization</akn:heading><akn:content><akn:p>(a) Authorization The Administrator is authorized to enter into such agreements with the pool formed or otherwise created under this part as he deems necessary to carry out the purposes of this chapter.</akn:p></akn:content></akn:subsection><akn:subsection eId="subsec_4052_b"><akn:num>(b)</akn:num><akn:heading>Terms and conditions</akn:heading><akn:content><akn:p>(b) Terms and conditions Such agreements shall specify—</akn:p></akn:content></akn:subsection><akn:subsection eId="subsec_4052_c"><akn:num>(c)</akn:num><akn:heading>Additional provisions</akn:heading><akn:content><akn:p>(c) Additional provisions In addition, such agreements shall contain such provisions as the Administrator finds necessary to assure that—</akn:p></akn:content></akn:subsection></akn:section></akn:body></akn:act></akn:akomaNtoso>