<?xml version="1.0" encoding="UTF-8"?>
<akn:akomaNtoso xmlns:akn="http://docs.oasis-open.org/legaldocml/ns/akn/3.0"><akn:act><akn:meta><akn:identification source="#cosilico"><akn:FRBRWork prescriptive="true" authoritative="true"><akn:FRBRuri value="/akn/us/usc/42/4156" /><akn:FRBRdate date="2025-12-31" name="retrieval" /><akn:FRBRauthor href="#us-congress" /><akn:FRBRcountry value="us" /></akn:FRBRWork><akn:FRBRExpression><akn:FRBRuri value="/akn/us/usc/42/4156/eng@2025" /><akn:FRBRdate date="2025-12-31" /><akn:FRBRauthor href="#cosilico" /><akn:FRBRlanguage language="en" /></akn:FRBRExpression><akn:FRBRManifestation><akn:FRBRuri value="/akn/us/usc/42/4156/eng@2025/main.xml" /><akn:FRBRdate date="2025-12-31" /><akn:FRBRauthor href="#cosilico" /></akn:FRBRManifestation></akn:identification></akn:meta><akn:body><akn:section eId="sec_4156"><akn:num>4156</akn:num><akn:heading>Waiver and modification of standards</akn:heading><akn:content><akn:p>§ 4156. Waiver and modification of standards
The Administrator of General Services, with respect to standards issued under section 4152 of this title, and the Secretary of Housing and Urban Development, with respect to standards issued under section 4153 of this title, and the Secretary of Defense with respect to standards issued under section 4154 of this title, and the United States Postal Service with respect to standards issued under section 4154a of this title—(1) is authorized to modify or waive any such standard, on a case-by-case basis, upon application made by the head of the department, agency, or instrumentality of the United States concerned, and upon a determination by the Administrator or Secretary, as the case may be, that such modification or waiver is clearly necessary, and

(2) shall establish a system of continuing surveys and investigations to insure compliance with such standards.

(Pub. L. 90–480, § 6, Aug. 12, 1968, 82 Stat. 719; Pub. L. 94–541, title II, § 201(6), Oct. 18, 1976, 90 Stat. 2508.)

Editorial Notes
Amendments1976—Pub. L. 94–541, in introductory text, inserted reference to the United States Postal Service with respect to standards issued under section 4154a of this title and struck out “is authorized” at end; in par. (1), inserted introductory words “is authorized”; and in par. (2), substituted “shall establish a system of continuing surveys and investigations” for “to conduct such surveys and investigations as he deems necessary”.</akn:p></akn:content><akn:subsection eId="subsec_4156_1"><akn:num>(1)</akn:num><akn:content><akn:p>(1) is authorized to modify or waive any such standard, on a case-by-case basis, upon application made by the head of the department, agency, or instrumentality of the United States concerned, and upon a determination by the Administrator or Secretary, as the case may be, that such modification or waiver is clearly necessary, and</akn:p></akn:content></akn:subsection><akn:subsection eId="subsec_4156_2"><akn:num>(2)</akn:num><akn:content><akn:p>(2) shall establish a system of continuing surveys and investigations to insure compliance with such standards.</akn:p></akn:content></akn:subsection></akn:section></akn:body></akn:act></akn:akomaNtoso>