<?xml version="1.0" encoding="UTF-8"?>
<akn:akomaNtoso xmlns:akn="http://docs.oasis-open.org/legaldocml/ns/akn/3.0"><akn:act><akn:meta><akn:identification source="#cosilico"><akn:FRBRWork prescriptive="true" authoritative="true"><akn:FRBRuri value="/akn/us/usc/36/21704" /><akn:FRBRdate date="2025-12-31" name="retrieval" /><akn:FRBRauthor href="#us-congress" /><akn:FRBRcountry value="us" /></akn:FRBRWork><akn:FRBRExpression><akn:FRBRuri value="/akn/us/usc/36/21704/eng@2025" /><akn:FRBRdate date="2025-12-31" /><akn:FRBRauthor href="#cosilico" /><akn:FRBRlanguage language="en" /></akn:FRBRExpression><akn:FRBRManifestation><akn:FRBRuri value="/akn/us/usc/36/21704/eng@2025/main.xml" /><akn:FRBRdate date="2025-12-31" /><akn:FRBRauthor href="#cosilico" /></akn:FRBRManifestation></akn:identification></akn:meta><akn:body><akn:section eId="sec_21704"><akn:num>21704</akn:num><akn:heading>Powers</akn:heading><akn:content><akn:p>§ 21704. Powers
The corporation may—(1) adopt a constitution, bylaws, and regulations to carry out the purposes of the corporation;

(2) adopt and alter a corporate seal;

(3) establish and maintain offices to conduct its activities;

(4) establish State and territorial organizations and local chapter or post organizations;

(5) provide guidance and leadership to organizations and local chapters established under paragraph (4), but may not control or otherwise influence the specific activities and conduct of such organizations and local chapters;

(6) acquire, own, lease, encumber, and transfer property as necessary to carry out the purposes of the corporation;

(7) publish a magazine and other publications;

(8) sue and be sued; and

(9) do any other act necessary and proper to carry out the purposes of the corporation.

(Pub. L. 105–225, Aug. 12, 1998, 112 Stat. 1297; Pub. L. 112–66, § 1, Dec. 13, 2011, 125 Stat. 768.)











Historical and Revision Notes


RevisedSectionSource (U.S. Code)Source (Statutes at Large)


2170436:44 (words before 4th semicolon less perpetual succession, words after 5th semicolon).Sept. 16, 1919, ch. 59, § 4 (words before 4th semicolon less perpetual succession, words after 5th semicolon), 41 Stat. 285; June 26, 1953, ch. 153, § 1, 67 Stat. 82.
 36:47.Sept. 16, 1919, ch. 59, § 7, 41 Stat. 285.


In this section, the text of 36:47 is omitted as executed and obsolete.
In clause (1), the words “not inconsistent with the laws of the United States or of any State” are omitted as unnecessary.
In clause (2), the words “at pleasure” are omitted as unnecessary.
In clause (3), the word “activities” is substituted for “business” for consistency in the revised title.
Clause (5) is substituted for “to receive, hold, own, use, and dispose of such real estate and personal property as shall be necessary for its corporate purposes” for consistency in the revised title and to eliminate unnecessary words.
In clause (7), the words “in courts of law and</akn:p></akn:content><akn:subsection eId="subsec_21704_1"><akn:num>(1)</akn:num><akn:content><akn:p>(1) adopt a constitution, bylaws, and regulations to carry out the purposes of the corporation;</akn:p></akn:content></akn:subsection><akn:subsection eId="subsec_21704_2"><akn:num>(2)</akn:num><akn:content><akn:p>(2) adopt and alter a corporate seal;</akn:p></akn:content></akn:subsection><akn:subsection eId="subsec_21704_3"><akn:num>(3)</akn:num><akn:content><akn:p>(3) establish and maintain offices to conduct its activities;</akn:p></akn:content></akn:subsection><akn:subsection eId="subsec_21704_4"><akn:num>(4)</akn:num><akn:content><akn:p>(4) establish State and territorial organizations and local chapter or post organizations;</akn:p></akn:content></akn:subsection><akn:subsection eId="subsec_21704_5"><akn:num>(5)</akn:num><akn:content><akn:p>(5) provide guidance and leadership to organizations and local chapters established under paragraph (4), but may not control or otherwise influence the specific activities and conduct of such organizations and local chapters;</akn:p></akn:content></akn:subsection><akn:subsection eId="subsec_21704_6"><akn:num>(6)</akn:num><akn:content><akn:p>(6) acquire, own, lease, encumber, and transfer property as necessary to carry out the purposes of the corporation;</akn:p></akn:content></akn:subsection><akn:subsection eId="subsec_21704_7"><akn:num>(7)</akn:num><akn:content><akn:p>(7) publish a magazine and other publications;</akn:p></akn:content></akn:subsection><akn:subsection eId="subsec_21704_8"><akn:num>(8)</akn:num><akn:content><akn:p>(8) sue and be sued; and</akn:p></akn:content></akn:subsection><akn:subsection eId="subsec_21704_9"><akn:num>(9)</akn:num><akn:content><akn:p>(9) do any other act necessary and proper to carry out the purposes of the corporation.</akn:p></akn:content></akn:subsection></akn:section></akn:body></akn:act></akn:akomaNtoso>