<?xml version="1.0" encoding="UTF-8"?>
<akn:akomaNtoso xmlns:akn="http://docs.oasis-open.org/legaldocml/ns/akn/3.0"><akn:act><akn:meta><akn:identification source="#cosilico"><akn:FRBRWork prescriptive="true" authoritative="true"><akn:FRBRuri value="/akn/us/usc/15/1141c" /><akn:FRBRdate date="2025-12-31" name="retrieval" /><akn:FRBRauthor href="#us-congress" /><akn:FRBRcountry value="us" /></akn:FRBRWork><akn:FRBRExpression><akn:FRBRuri value="/akn/us/usc/15/1141c/eng@2025" /><akn:FRBRdate date="2025-12-31" /><akn:FRBRauthor href="#cosilico" /><akn:FRBRlanguage language="en" /></akn:FRBRExpression><akn:FRBRManifestation><akn:FRBRuri value="/akn/us/usc/15/1141c/eng@2025/main.xml" /><akn:FRBRdate date="2025-12-31" /><akn:FRBRauthor href="#cosilico" /></akn:FRBRManifestation></akn:identification></akn:meta><akn:body><akn:section eId="sec_1141c"><akn:num>1141c</akn:num><akn:heading>Restriction, abandonment, cancellation, or expiration of a basic application or basic registration</akn:heading><akn:content><akn:p>§ 1141c. Restriction, abandonment, cancellation, or expiration of a basic application or basic registration
With respect to an international application transmitted to the International Bureau under section 1141b of this title, the Director shall notify the International Bureau whenever the basic application or basic registration which is the basis for the international application has been restricted, abandoned, or canceled, or has expired, with respect to some or all of the goods and services listed in the international registration—(1) within 5 years after the international registration date; or

(2) more than 5 years after the international registration date if the restriction, abandonment, or cancellation of the basic application or basic registration resulted from an action that began before the end of that 5-year period.

(July 5, 1946, ch. 540, title XII, § 63, as added Pub. L. 107–273, div. C, title III, § 13402, Nov. 2, 2002, 116 Stat. 1915.)</akn:p></akn:content><akn:subsection eId="subsec_1141c_1"><akn:num>(1)</akn:num><akn:content><akn:p>(1) within 5 years after the international registration date; or</akn:p></akn:content></akn:subsection><akn:subsection eId="subsec_1141c_2"><akn:num>(2)</akn:num><akn:content><akn:p>(2) more than 5 years after the international registration date if the restriction, abandonment, or cancellation of the basic application or basic registration resulted from an action that began before the end of that 5-year period.</akn:p></akn:content></akn:subsection></akn:section></akn:body></akn:act></akn:akomaNtoso>